jpconfig/__init__.py
jpconfig/jpconfig.py
test/__init__.py
test/test_jpconfig.py
jp_config-1.0.0.dist-info/METADATA
jp_config-1.0.0.dist-info/WHEEL
jp_config-1.0.0.dist-info/top_level.txt
jp_config-1.0.0.dist-info/RECORD
