Metadata-Version: 2.1
Name: jp-config
Version: 1.0.0
Summary: dict to json file object.
Home-page: UNKNOWN
Author: James Phillips
Author-email: james@mightysteedit.co.uk
License: GPLv3
Platform: UNKNOWN
